{
  "chapter": "PART 07 유닛로드시스템(ULS)",
  "subject": "화물운송론",
  "quizzes": [
    {
      "id": "q2-07-01",
      "type": "concept",
      "format": "multiple_choice",
      "difficulty": 1,
      "topic": "ULS 개념",
      "question": "유닛로드시스템(ULS)의 효과로 가장 거리가 먼 것은?",
      "options": [
        "A. 하역 횟수 감소",
        "B. 화물 파손율 저하",
        "C. 포장비 절감",
        "D. 운송수단의 속도 향상",
        "E. 하역시간 단축"
      ],
      "answer": "D",
      "explanation": "유닛로드시스템은 하역 효율화가 핵심 목적으로, 하역횟수 감소·하역시간 단축·파손율 저하·포장비 절감 등의 효과가 있다. 운송수단 자체의 속도 향상은 ULS의 효과가 아니다.",
      "relatedConcept": "유닛로드시스템(ULS)의 개념",
      "examTip": "ULS는 '하역 효율화'가 핵심. 운송 속도·운임과는 직접 관련 없음"
    },
    {
      "id": "q2-07-02",
      "type": "exam",
      "format": "multiple_choice",
      "difficulty": 1,
      "topic": "한국 표준 팔레트",
      "question": "한국의 표준 팔레트 규격(T-11형)의 치수는?",
      "options": [
        "A. 1,200mm × 1,000mm",
        "B. 1,200mm × 800mm",
        "C. 1,100mm × 1,100mm",
        "D. 1,067mm × 1,067mm",
        "E. 1,219mm × 1,016mm"
      ],
      "answer": "C",
      "explanation": "한국 표준 팔레트 T-11형은 1,100mm × 1,100mm의 정사각형 규격이다. A는 유럽형, B는 유로팔레트, D는 호주·북미형, E는 미국 GMA 팔레트이다.",
      "relatedConcept": "팔레트(Pallet)",
      "examTip": "T-11형 = 1,100 × 1,100mm. 가장 자주 출제되는 규격. '11×11'로 암기"
    },
    {
      "id": "q2-07-03",
      "type": "exam",
      "format": "multiple_choice",
      "difficulty": 2,
      "topic": "컨테이너 규격",
      "question": "ISO 표준 20피트 컨테이너(TEU)의 외부 치수로 올바른 것은?",
      "options": [
        "A. 길이 20' × 폭 8' × 높이 8'",
        "B. 길이 20' × 폭 8' × 높이 8'6\"",
        "C. 길이 20' × 폭 8'6\" × 높이 8'6\"",
        "D. 길이 20' × 폭 10' × 높이 8'6\"",
        "E. 길이 20' × 폭 8' × 높이 9'6\""
      ],
      "answer": "B",
      "explanation": "ISO 표준 20피트 컨테이너의 외부 치수는 길이 20피트 × 폭 8피트 × 높이 8피트 6인치이다. 폭 8피트, 높이 8'6\"는 20ft와 40ft 모두 동일하며, 길이만 다르다. E는 하이큐브(9'6\")의 높이이다.",
      "relatedConcept": "컨테이너(Container)의 종류와 규격",
      "examTip": "20ft/40ft 공통: 폭 8', 높이 8'6\". 하이큐브만 높이 9'6\". 폭이나 높이를 다르게 제시하면 오답"
    },
    {
      "id": "q2-07-04",
      "type": "exam",
      "format": "multiple_choice",
      "difficulty": 2,
      "topic": "컨테이너 종류",
      "question": "지붕이 개방되어 있어 천막(Tarpaulin)으로 덮는 방식의 컨테이너로, 대형 기계·목재 등 높이가 높은 화물에 적합한 것은?",
      "options": [
        "A. 드라이 컨테이너(Dry Container)",
        "B. 냉동 컨테이너(Reefer Container)",
        "C. 오픈탑 컨테이너(Open Top Container)",
        "D. 플랫랙 컨테이너(Flat Rack Container)",
        "E. 탱크 컨테이너(Tank Container)"
      ],
      "answer": "C",
      "explanation": "오픈탑 컨테이너(Open Top Container)는 지붕이 개방되어 천막으로 덮는 방식으로, 크레인을 이용한 상부 적재가 가능하여 대형 기계·목재 등 높이가 높은 화물에 적합하다.",
      "relatedConcept": "컨테이너(Container)의 종류와 규격",
      "examTip": "오픈탑=지붕 개방(상부 적재), 플랫랙=측벽·지붕 없음(초대형). 개방 부위로 구분"
    },
    {
      "id": "q2-07-05",
      "type": "exam",
      "format": "multiple_choice",
      "difficulty": 2,
      "topic": "CY와 CFS",
      "question": "CFS(Container Freight Station)에서 수행되는 주요 작업으로 옳은 것은?",
      "options": [
        "A. FCL 컨테이너의 장치·보관",
        "B. 컨테이너 선박의 접안",
        "C. LCL 화물의 적입(Stuffing)과 적출(Stripping)",
        "D. 컨테이너의 반출입 검사",
        "E. 갠트리 크레인에 의한 양·적하"
      ],
      "answer": "C",
      "explanation": "CFS(Container Freight Station)는 LCL(소량 화물)의 적입(Stuffing: 컨테이너에 넣기)과 적출(Stripping: 컨테이너에서 꺼내기)을 수행하는 장소이다. A는 CY, D는 게이트, E는 에이프런의 기능이다.",
      "relatedConcept": "컨테이너 터미널 운영",
      "examTip": "CFS=LCL 화물의 Stuffing/Stripping, CY=FCL 컨테이너 보관. 절대 혼동하지 말 것"
    },
    {
      "id": "q2-07-06",
      "type": "concept",
      "format": "ox",
      "difficulty": 1,
      "topic": "TEU와 FEU",
      "question": "40피트 컨테이너 1개는 2TEU에 해당한다.",
      "options": [],
      "answer": "O",
      "explanation": "TEU(Twenty-foot Equivalent Unit)는 20피트 컨테이너 1개를 기준 단위로 한다. 40피트 컨테이너(FEU) 1개는 20피트의 2배이므로 2TEU에 해당한다.",
      "relatedConcept": "컨테이너(Container)의 종류와 규격",
      "examTip": "1FEU = 2TEU. 선박 용량 계산 시 40ft를 2TEU로 환산"
    },
    {
      "id": "q2-07-07",
      "type": "exam",
      "format": "multiple_choice",
      "difficulty": 2,
      "topic": "일관파레티제이션",
      "question": "일관파레티제이션(Through Palletization)의 실현 조건에 해당하지 않는 것은?",
      "options": [
        "A. 팔레트 규격의 표준화",
        "B. 운송수단의 팔레트 적재 호환성",
        "C. 하역장비의 표준화",
        "D. 모든 화물의 컨테이너화",
        "E. 보관시설(랙)의 팔레트 규격 호환"
      ],
      "answer": "D",
      "explanation": "일관파레티제이션은 팔레트 단위의 일관 운송으로, 컨테이너화와는 다른 개념이다. 실현 조건은 팔레트 규격 표준화, 운송수단·하역장비·보관시설의 호환성이며, '컨테이너화'는 관련 없다.",
      "relatedConcept": "일관파레티제이션(Through Palletization)",
      "examTip": "일관파레티제이션 ≠ 컨테이너화. 팔레트와 컨테이너를 혼동시키는 함정"
    },
    {
      "id": "q2-07-08",
      "type": "exam",
      "format": "multiple_choice",
      "difficulty": 2,
      "topic": "팔레트 출입구",
      "question": "4방향(Four-way) 팔레트에 대한 설명으로 옳은 것은?",
      "options": [
        "A. 지게차가 4면 중 2면에서만 진입 가능하다",
        "B. 팔레트의 4면 모두에서 지게차 포크 진입이 가능하다",
        "C. 4단까지만 적재가 가능한 팔레트이다",
        "D. 4종류의 화물을 동시에 적재할 수 있는 팔레트이다",
        "E. 상면이 4개의 구역으로 나뉜 팔레트이다"
      ],
      "answer": "B",
      "explanation": "4방향(Four-way) 팔레트는 4면 모두에서 지게차 포크의 진입이 가능한 팔레트로, 하역 편의성이 높다. 2방향(Two-way) 팔레트는 2면에서만 진입 가능하다.",
      "relatedConcept": "팔레트(Pallet)",
      "examTip": "4방향=4면 진입(편리), 2방향=2면 진입. '방향'은 지게차 진입 방향을 의미"
    },
    {
      "id": "q2-07-09",
      "type": "exam",
      "format": "multiple_choice",
      "difficulty": 2,
      "topic": "하역장비",
      "question": "컨테이너 터미널의 안벽(Quay)에서 선박과 에이프런 사이의 컨테이너 양·적하 작업에 사용되는 대형 크레인은?",
      "options": [
        "A. RTGC(Rubber Tired Gantry Crane)",
        "B. RMGC(Rail Mounted Gantry Crane)",
        "C. 갠트리 크레인(Quay Crane/QC)",
        "D. 스트래들 캐리어(Straddle Carrier)",
        "E. 리치 스태커(Reach Stacker)"
      ],
      "answer": "C",
      "explanation": "갠트리 크레인(Quay Crane/QC)은 안벽에 설치되어 선박과 에이프런 사이에서 컨테이너를 양·적하하는 대형 크레인이다. RTGC와 RMGC는 야드 내 적재용, 스트래들 캐리어는 야드 내 이동용이다.",
      "relatedConcept": "컨테이너 터미널 운영",
      "examTip": "안벽(선박↔에이프런)=갠트리/QC, 야드 내=RTGC/RMGC/S/C. 작업 위치로 장비 구분"
    },
    {
      "id": "q2-07-10",
      "type": "exam",
      "format": "multiple_choice",
      "difficulty": 3,
      "topic": "RTGC vs RMGC",
      "question": "컨테이너 야드 크레인 중 자동화 터미널에 적합하며 레일 위를 주행하는 장비는?",
      "options": [
        "A. RTGC(Rubber Tired Gantry Crane)",
        "B. RMGC(Rail Mounted Gantry Crane)",
        "C. 갠트리 크레인(Quay Crane)",
        "D. 스트래들 캐리어(Straddle Carrier)",
        "E. 리치 스태커(Reach Stacker)"
      ],
      "answer": "B",
      "explanation": "RMGC(Rail Mounted Gantry Crane)는 레일 위를 주행하는 야드 크레인으로, 정밀한 위치 제어가 가능하여 자동화 터미널에 적합하다. RTGC는 타이어식으로 이동성은 높지만 자동화에는 RMGC가 유리하다.",
      "relatedConcept": "컨테이너 터미널 운영",
      "examTip": "RMGC=레일+자동화, RTGC=타이어+유연성. 자동화 터미널 관련 문제는 RMGC"
    },
    {
      "id": "q2-07-11",
      "type": "concept",
      "format": "ox",
      "difficulty": 2,
      "topic": "하이큐브 컨테이너",
      "question": "하이큐브(High Cube) 컨테이너는 일반 컨테이너와 폭은 같지만 높이가 9피트 6인치로 일반보다 1피트 높다.",
      "options": [],
      "answer": "O",
      "explanation": "하이큐브(High Cube) 컨테이너는 일반 컨테이너(높이 8'6\")보다 1피트 높은 9피트 6인치(2,896mm)의 높이를 가진다. 폭(8피트)과 길이(20' 또는 40')는 동일하다.",
      "relatedConcept": "컨테이너(Container)의 종류와 규격",
      "examTip": "하이큐브=높이 9'6\"(일반 8'6\" + 1피트). 폭과 길이는 동일"
    },
    {
      "id": "q2-07-12",
      "type": "exam",
      "format": "multiple_choice",
      "difficulty": 2,
      "topic": "운송조건",
      "question": "한 명의 화주가 컨테이너 1개를 독점 사용하여 출발지 CY에서 적입하고 도착지 CY에서 수하인이 직접 적출하는 운송 조건은?",
      "options": [
        "A. CFS/CFS",
        "B. CY/CFS",
        "C. CFS/CY",
        "D. CY/CY",
        "E. Door/Door"
      ],
      "answer": "D",
      "explanation": "CY/CY는 출발지 CY에서 화주가 직접 적입(FCL)하고, 도착지 CY에서 수하인이 직접 적출(FCL)하는 조건이다. 한 화주가 컨테이너를 독점 사용하는 FCL 화물에 적용된다.",
      "relatedConcept": "컨테이너 터미널 운영",
      "examTip": "CY/CY=FCL/FCL(한 화주 독점), CFS/CFS=LCL/LCL(소량 혼적). 출발·도착 조합 4가지 정리"
    },
    {
      "id": "q2-07-13",
      "type": "exam",
      "format": "multiple_choice",
      "difficulty": 2,
      "topic": "팔레트 풀",
      "question": "팔레트 풀(Pallet Pool) 시스템의 장점이 아닌 것은?",
      "options": [
        "A. 빈 팔레트 회수 비용 절감",
        "B. 팔레트 이용률 향상",
        "C. 일관파레티제이션 촉진",
        "D. 팔레트 규격의 다양화 촉진",
        "E. 팔레트 관리 비용 절감"
      ],
      "answer": "D",
      "explanation": "팔레트 풀 시스템은 팔레트를 공동으로 사용·관리하는 제도로, 오히려 팔레트 규격의 '표준화'를 촉진한다. 규격의 다양화는 팔레트 풀의 목적과 반대되는 개념이다.",
      "relatedConcept": "일관파레티제이션(Through Palletization)",
      "examTip": "팔레트 풀 = 표준화 촉진. '다양화'는 반대 개념으로 오답"
    },
    {
      "id": "q2-07-14",
      "type": "exam",
      "format": "multiple_choice",
      "difficulty": 3,
      "topic": "컨테이너 적재량",
      "question": "20피트 컨테이너의 최대총중량(Max Gross Weight)이 30,480kg이고 자체중량(Tare Weight)이 2,300kg일 때, 최대적재량(Max Payload)은?",
      "options": [
        "A. 30,480kg",
        "B. 28,180kg",
        "C. 32,780kg",
        "D. 26,680kg",
        "E. 27,180kg"
      ],
      "answer": "B",
      "explanation": "최대적재량(Max Payload) = 최대총중량(Max Gross Weight) - 자체중량(Tare Weight) = 30,480 - 2,300 = 28,180kg.",
      "relatedConcept": "컨테이너(Container)의 종류와 규격",
      "examTip": "Payload = Gross - Tare. 20ft: 30,480-2,300=28,180kg. 단순하지만 자주 출제되는 계산"
    },
    {
      "id": "q2-07-15",
      "type": "exam",
      "format": "multiple_choice",
      "difficulty": 2,
      "topic": "컨테이너 규격 표준화",
      "question": "컨테이너의 외부 치수·강도·시험방법 등의 국제표준을 제정하는 기관은?",
      "options": [
        "A. IATA(국제항공운송협회)",
        "B. IMO(국제해사기구)",
        "C. ISO(국제표준화기구)",
        "D. FIATA(국제운송주선인협회)",
        "E. UNCTAD(유엔무역개발회의)"
      ],
      "answer": "C",
      "explanation": "해상 컨테이너의 외부 치수(ISO 668), 강도·시험방법(ISO 1496), 코딩·식별(ISO 6346) 등의 국제표준은 ISO(International Organization for Standardization)에서 제정한다.",
      "relatedConcept": "컨테이너(Container)의 종류와 규격",
      "examTip": "해상 컨테이너=ISO 규격, 항공 ULD=IATA 규격. 표준화 기관 구분 필수"
    },
    {
      "id": "q2-07-16",
      "type": "exam",
      "format": "multiple_choice",
      "difficulty": 2,
      "topic": "PPS 종류",
      "question": "팔레트풀시스템(PPS) 중 유럽 국영철도에서 사용하며, 화주가 개별적으로 팔레트를 보유하는 방식은?",
      "options": [
        "A. 리스방식",
        "B. 렌탈방식",
        "C. 즉시교환방식",
        "D. 공유방식",
        "E. 위탁방식"
      ],
      "answer": "C",
      "explanation": "즉시교환방식은 유럽 국영철도에서 사용하는 방식으로, 화주가 개별적으로 팔레트를 보유하고 즉시 교환하여 분실을 방지한다.",
      "relatedConcept": "팔레트풀시스템(PPS)의 종류",
      "examTip": "즉시교환=유럽 철도+화주 보유+분실방지, 리스렌탈=회사 임대+품질유지"
    },
    {
      "id": "q2-07-17",
      "type": "exam",
      "format": "multiple_choice",
      "difficulty": 2,
      "topic": "ITI 협약",
      "question": "육·해·공 모든 운송수단을 대상으로 하는 국제운송에 관한 통관조약은?",
      "options": [
        "A. ITI 협약",
        "B. TIR 협약",
        "C. ICSC 협약",
        "D. CSI",
        "E. ISPS Code"
      ],
      "answer": "A",
      "explanation": "ITI 협약(국제통과화물에 관한 통관협약)은 육·해·공 모든 운송수단을 대상으로 한다. TIR은 도로운송, ICSC는 컨테이너안전 관련이다.",
      "relatedConcept": "컨테이너 관련 국제협약과 터미널 시설",
      "examTip": "ITI=전 운송수단(육해공), TIR=도로 전용, ICSC=안전 전용"
    },
    {
      "id": "q2-07-18",
      "type": "exam",
      "format": "multiple_choice",
      "difficulty": 2,
      "topic": "마샬링 야드",
      "question": "컨테이너 터미널에서 선적예정 컨테이너를 적치계획에 따라 순서대로 쌓아두는 장소는?",
      "options": [
        "A. 에이프런",
        "B. CFS",
        "C. CY",
        "D. 마샬링 야드",
        "E. 게이트"
      ],
      "answer": "D",
      "explanation": "마샬링 야드(Marshalling Yard)는 본선 입항 전에 선내 적치계획에 따라 선적예정 컨테이너를 순서대로 쌓아두는 곳으로, 터미널 운영의 중심이 된다.",
      "relatedConcept": "컨테이너 관련 국제협약과 터미널 시설",
      "examTip": "마샬링 야드=선적순서 배열+터미널 중심. 에이프런=안벽 접한 크레인 통과구간"
    },
    {
      "id": "q2-07-19",
      "type": "exam",
      "format": "multiple_choice",
      "difficulty": 2,
      "topic": "Consolidation",
      "question": "CY(FCL)에서 출발하여 CFS(LCL)로 도착하는 컨테이너화물 운송형태는?",
      "options": [
        "A. Buyer's Consolidation",
        "B. Forwarder's Consolidation",
        "C. Shipper's Consolidation",
        "D. Door/Door",
        "E. Carrier's Consolidation"
      ],
      "answer": "C",
      "explanation": "CY(FCL)→CFS(LCL)은 Shipper's Consolidation이다. 송화인이 FCL로 적입하여 보내면 도착지 CFS에서 개별 화주에게 분류된다.",
      "relatedConcept": "컨테이너화물 운송형태(Consolidation)",
      "examTip": "CY→CFS=Shipper's, CFS→CY=Buyer's, CFS→CFS=Forwarder's"
    },
    {
      "id": "q2-07-20",
      "type": "concept",
      "format": "ox",
      "difficulty": 1,
      "topic": "개별포장",
      "question": "컨테이너가 포장용기의 역할을 하므로 컨테이너 내부 화물의 개별포장은 불필요하다.",
      "options": [],
      "answer": "X",
      "explanation": "컨테이너가 포장용기의 역할을 하지만, 개별포장이 불필요한 것은 아니다. 컨테이너 내부에서의 화물 보호를 위해 개별포장은 여전히 필요하다.",
      "relatedConcept": "컨테이너 관련 국제협약과 터미널 시설",
      "examTip": "컨테이너=외부포장 역할, 개별포장=여전히 필요. '불필요'라고 하면 오답"
    },
    {
      "id": "q2-07-21",
      "type": "exam",
      "format": "multiple_choice",
      "difficulty": 2,
      "topic": "스트래들 캐리어",
      "question": "컨테이너를 양각(다리) 사이에 들어올려 주행하는 야드 내 이동장비는?",
      "options": [
        "A. 갠트리 크레인",
        "B. 리치 스태커",
        "C. 스트래들 캐리어",
        "D. RTGC",
        "E. 야드 트랙터"
      ],
      "answer": "C",
      "explanation": "스트래들 캐리어(Straddle Carrier)는 컨테이너를 양각(다리) 사이에 들어올려 주행하는 야드 내 이동장비이다.",
      "relatedConcept": "컨테이너 터미널 운영",
      "examTip": "스트래들 캐리어=양각 사이에 끼워서 이동. 트랜스테이너=쌓고 내리기+야드 면적 가장 큼"
    },
    {
      "id": "q2-07-22",
      "type": "exam",
      "format": "multiple_choice",
      "difficulty": 2,
      "topic": "트랜스테이너",
      "question": "컨테이너 터미널에서 야드의 필요면적이 가장 크고 많은 자본이 필요한 하역방식은?",
      "options": [
        "A. 갠트리 크레인 방식",
        "B. 스트래들 캐리어 방식",
        "C. 트랜스테이너 방식",
        "D. 리치 스태커 방식",
        "E. 섀시 방식"
      ],
      "answer": "C",
      "explanation": "트랜스테이너 방식은 컨테이너를 쌓거나 내리는 작업, 섀시나 트레일러에 싣고 내리는 작업을 수행하며, 야드의 필요면적이 가장 크고 많은 자본이 필요하다.",
      "relatedConcept": "컨테이너 터미널 운영",
      "examTip": "트랜스테이너=야드면적 가장 큼+자본 많이 필요. 면적/자본 관련 문제 출제 빈출"
    },
    {
      "id": "q2-07-23",
      "type": "exam",
      "format": "multiple_choice",
      "difficulty": 2,
      "topic": "윈치크레인",
      "question": "크레인 자체를 회전시키면서 컨테이너를 양·적하하는 장비는?",
      "options": [
        "A. 갠트리 크레인",
        "B. 윈치크레인",
        "C. RTGC",
        "D. RMGC",
        "E. 리치 스태커"
      ],
      "answer": "B",
      "explanation": "윈치크레인은 크레인 자체를 회전시키면서 컨테이너를 양·적하하는 장비이다. 갠트리 크레인은 안벽에서 수직 양·적하를 수행한다.",
      "relatedConcept": "컨테이너 터미널 운영",
      "examTip": "윈치크레인=회전+양적하. 갠트리=안벽 수직, RTGC/RMGC=야드 내"
    },
    {
      "id": "q2-07-24",
      "type": "exam",
      "format": "multiple_choice",
      "difficulty": 2,
      "topic": "유로팔레트",
      "question": "유럽에서 널리 사용되는 유로팔레트(EUR 팔레트)의 규격은?",
      "options": [
        "A. 1,100mm × 1,100mm",
        "B. 1,200mm × 1,000mm",
        "C. 1,200mm × 800mm",
        "D. 1,067mm × 1,067mm",
        "E. 1,219mm × 1,016mm"
      ],
      "answer": "C",
      "explanation": "유로팔레트는 1,200mm × 800mm 규격이다. 한국 T-11형은 1,100×1,100mm, 유럽형(ISO)은 1,200×1,000mm, 미국 GMA는 1,219×1,016mm이다.",
      "relatedConcept": "팔레트(Pallet)",
      "examTip": "유로=1,200×800, T-11(한국)=1,100×1,100, 유럽ISO=1,200×1,000"
    },
    {
      "id": "q2-07-25",
      "type": "exam",
      "format": "multiple_choice",
      "difficulty": 2,
      "topic": "항공 ULD",
      "question": "항공기 ULD(Unit Load Device)에 대한 설명으로 옳지 않은 것은?",
      "options": [
        "A. 항공형 컨테이너, 파렛트, 이글루 등이 포함된다",
        "B. 항공기 기종 간 호환성이 높다",
        "C. IATA 규정에 의해 외면표기가 의무화되어 있다",
        "D. 적재 위치별로 내부공간이 다르다",
        "E. 견인차에 연결된 돌리로 이동된다"
      ],
      "answer": "B",
      "explanation": "항공기 ULD는 기종별로 규격이 표준화되어 있지 않아 기종 간 호환성이 '낮은' 편이다. 호환성이 높다고 하면 오답이다.",
      "relatedConcept": "컨테이너(Container)의 종류와 규격",
      "examTip": "항공 ULD=기종 간 호환성 낮음. 해상 컨테이너=ISO 표준화(호환성 높음)"
    }
  ]
}