{
  "chapter": "PART 05 물류비 회계",
  "subject": "물류관리론",
  "quizzes": [
    {
      "id": "q1-05-01",
      "type": "concept",
      "format": "multiple_choice",
      "difficulty": 1,
      "topic": "물류비 기능별 분류",
      "question": "다음 중 물류비의 기능별 분류에 해당하지 않는 것은?",
      "options": [
        "A. 운송비",
        "B. 보관비",
        "C. 조달물류비",
        "D. 하역비",
        "E. 포장비"
      ],
      "answer": "C",
      "explanation": "조달물류비는 기능별 분류가 아니라 '영역별 분류'에 해당한다. 기능별 분류는 운송비, 보관비, 하역비, 포장비, 물류정보비, 물류관리비의 6가지이다.",
      "relatedConcept": "물류비의 개념과 분류체계",
      "examTip": "기능별 6분류(운보하포정관)와 영역별 5분류(조달·사내·판매·반품·폐기)를 혼동하지 않도록 구분해서 암기하자."
    },
    {
      "id": "q1-05-02",
      "type": "exam",
      "format": "multiple_choice",
      "difficulty": 2,
      "topic": "포장비의 물류비 포함 여부",
      "question": "물류비에 포함되는 포장비로 가장 적절한 것은?",
      "options": [
        "A. 상품의 판매촉진을 위한 포장비용",
        "B. 소비자에게 매력적으로 보이기 위한 디자인 포장비",
        "C. 수송·보관 중 화물 보호를 위한 공업포장비",
        "D. 브랜드 이미지 강화를 위한 고급 포장재 비용",
        "E. 매장 진열을 위한 디스플레이 포장비"
      ],
      "answer": "C",
      "explanation": "물류비에 포함되는 포장비는 '공업포장(물류포장)' 비용만 해당된다. 수송·보관 중 화물을 보호하기 위한 목적의 포장이다. 상업포장(판매촉진, 소비자 대상, 디자인, 브랜드)은 판매비(마케팅비)로 분류되어 물류비에 포함되지 않는다.",
      "relatedConcept": "물류비의 개념과 분류체계",
      "examTip": "포장비 문제는 단골 출제. '물류포장=공업포장=수송포장'은 물류비, '상업포장=판매포장=소비자포장'은 물류비 아님."
    },
    {
      "id": "q1-05-03",
      "type": "concept",
      "format": "ox",
      "difficulty": 1,
      "topic": "매크로·마이크로 물류비",
      "question": "국가 전체의 물류비(매크로 물류비)는 매출액 대비 비율로 측정한다.",
      "options": [],
      "answer": "X",
      "explanation": "국가 전체의 물류비(매크로/거시 물류비)는 GDP 대비 비율로 측정한다. 매출액 대비 비율로 측정하는 것은 개별 기업의 물류비(마이크로/미시 물류비)이다.",
      "relatedConcept": "물류비 산정기준과 물류비 계산",
      "examTip": "매크로=GDP 대비, 마이크로=매출액 대비. 바꿔서 출제하는 것이 단골 함정."
    },
    {
      "id": "q1-05-04",
      "type": "exam",
      "format": "multiple_choice",
      "difficulty": 2,
      "topic": "물류비 배부",
      "question": "물류비 배부(배분)에 대한 설명으로 가장 옳지 않은 것은?",
      "options": [
        "A. 직접물류비는 배부 과정 없이 원가대상에 직접 귀속시킨다",
        "B. 간접물류비는 합리적 배부기준에 따라 배분한다",
        "C. 배부기준으로 중량, 용적, 건수, 금액 등이 사용된다",
        "D. 모든 물류비는 배부 과정을 거쳐야 한다",
        "E. 배부기준은 원가 발생과의 인과관계를 고려하여 선정한다"
      ],
      "answer": "D",
      "explanation": "모든 물류비가 배부 과정을 거치는 것은 아니다. 직접물류비는 특정 원가대상에 직접 추적·귀속이 가능하므로 배부 과정이 불필요하다. 배부가 필요한 것은 여러 원가대상에 공통으로 발생하는 간접물류비뿐이다.",
      "relatedConcept": "물류비 산정기준과 물류비 계산",
      "examTip": "직접비는 직접 귀속, 간접비만 배부. '모든', '항상' 같은 절대 표현이 포함된 보기는 오답일 가능성이 높다."
    },
    {
      "id": "q1-05-05",
      "type": "exam",
      "format": "multiple_choice",
      "difficulty": 2,
      "topic": "ABC 원가계산",
      "question": "활동기준원가계산(ABC)에서 사용되는 원가동인(Cost Driver) 중 정확도는 가장 높지만 측정비용이 가장 많이 드는 유형은?",
      "options": [
        "A. 거래동인(Transaction Driver)",
        "B. 기간동인(Duration Driver)",
        "C. 강도동인(Intensity Driver)",
        "D. 물량동인(Volume Driver)",
        "E. 배치동인(Batch Driver)"
      ],
      "answer": "C",
      "explanation": "강도동인(Intensity Driver)은 활동의 복잡성·난이도를 기준으로 원가를 배분하는 것으로, 정확도가 가장 높지만 측정에 드는 비용도 가장 높다. 거래동인은 횟수 기준으로 측정이 간편하나 정확도가 낮고, 기간동인은 소요시간 기준으로 중간 수준이다.",
      "relatedConcept": "활동기준원가계산(ABC)",
      "examTip": "원가동인 정확도 순서: 강도 > 기간 > 거래. 측정비용도 같은 순서. D, E는 ABC에서 공식적으로 분류하는 3가지 유형이 아니므로 혼동 주의."
    },
    {
      "id": "q1-05-06",
      "type": "exam",
      "format": "multiple_choice",
      "difficulty": 3,
      "topic": "ABC 원가계산 적용",
      "question": "ABC(활동기준원가계산)에 대한 설명으로 옳지 않은 것은?",
      "options": [
        "A. 간접비 비중이 높은 기업에 적용 효과가 크다",
        "B. 다품종 소량생산 환경에서 전통적 원가계산보다 정확하다",
        "C. 원가동인(Cost Driver)을 활용하여 원가를 배분한다",
        "D. ABC는 제품원가 산정에만 활용되며 고객별 수익성 분석에는 적용할 수 없다",
        "E. 도입 및 운영 비용이 전통적 원가계산보다 높다"
      ],
      "answer": "D",
      "explanation": "ABC는 제품원가 산정뿐만 아니라 고객별 수익성 분석, 채널별 물류비 분석, 비부가가치 활동 식별 등 다양한 목적에 활용된다. 특히 물류 분야에서는 고객별·경로별·채널별 물류비를 정확히 파악하여 수익성을 분석하는 데 매우 유용하다.",
      "relatedConcept": "활동기준원가계산(ABC)",
      "examTip": "ABC의 활용범위를 좁게 한정하는 보기는 오답. ABC는 제품·고객·채널·프로세스 등 다양한 원가대상에 적용 가능하다."
    },
    {
      "id": "q1-05-07",
      "type": "exam",
      "format": "multiple_choice",
      "difficulty": 3,
      "topic": "ABC 계산문제",
      "question": "보관활동의 원가풀이 8,000만 원이고, 원가동인을 보관면적(㎡)으로 설정하였다. 총 보관면적이 2,000㎡이고, A제품의 보관면적이 500㎡일 때, A제품에 배부될 보관비는?",
      "options": [
        "A. 1,000만 원",
        "B. 2,000만 원",
        "C. 2,500만 원",
        "D. 3,000만 원",
        "E. 4,000만 원"
      ],
      "answer": "B",
      "explanation": "원가동인율 = 8,000만 원 ÷ 2,000㎡ = 4만 원/㎡. A제품 배부액 = 4만 원/㎡ × 500㎡ = 2,000만 원.",
      "relatedConcept": "활동기준원가계산(ABC)",
      "examTip": "ABC 계산문제 풀이 순서: ①원가동인율 산출(원가풀÷동인총량) → ②배부액 산출(동인율×소비량). 반드시 단계별로 계산하자."
    },
    {
      "id": "q1-05-08",
      "type": "exam",
      "format": "multiple_choice",
      "difficulty": 2,
      "topic": "손익분기점 분석",
      "question": "물류센터의 월 고정비가 6,000만 원이고, 공헌이익률이 40%일 때, 손익분기점 매출액은?",
      "options": [
        "A. 1억 원",
        "B. 1억 2,000만 원",
        "C. 1억 5,000만 원",
        "D. 2억 원",
        "E. 2억 4,000만 원"
      ],
      "answer": "C",
      "explanation": "BEP 매출액 = 고정비 ÷ 공헌이익률 = 6,000만 원 ÷ 0.4 = 1억 5,000만 원. 이 매출액 이상을 달성해야 손익분기를 넘어 이익이 발생한다.",
      "relatedConcept": "물류원가계산과 손익분석",
      "examTip": "BEP 매출액 = 고정비 ÷ 공헌이익률. 공헌이익률 = 1 - 변동비율임을 기억하자."
    },
    {
      "id": "q1-05-09",
      "type": "exam",
      "format": "multiple_choice",
      "difficulty": 3,
      "topic": "자가 vs 위탁 의사결정",
      "question": "자가물류의 고정비가 8,000만 원, 단위당 변동비가 3,000원이고, 위탁물류의 고정비가 2,000만 원, 단위당 변동비가 9,000원일 때, 손익분기물량은 얼마이며, 연간 물량이 12,000개일 때 어떤 방식이 유리한가?",
      "options": [
        "A. 손익분기물량 8,000개, 자가물류 유리",
        "B. 손익분기물량 10,000개, 자가물류 유리",
        "C. 손익분기물량 10,000개, 위탁물류 유리",
        "D. 손익분기물량 12,000개, 자가물류 유리",
        "E. 손익분기물량 8,000개, 위탁물류 유리"
      ],
      "answer": "B",
      "explanation": "8,000만 + 3,000Q = 2,000만 + 9,000Q → 6,000만 = 6,000Q → Q = 10,000개. 연간 물량 12,000개는 손익분기물량 10,000개보다 많으므로 자가물류가 유리하다. (자가: 8,000만+3,000×12,000=4억4,000만, 위탁: 2,000만+9,000×12,000=10억10,000만 → 자가가 유리 확인). 수정: 자가=8,000만+3,600만=1억1,600만, 위탁=2,000만+1억800만=1억2,800만. 자가가 더 저렴.",
      "relatedConcept": "물류원가계산과 손익분석",
      "examTip": "자가 vs 위탁 문제: ①손익분기물량 구하기(고정비 차이÷변동비 차이) → ②실제물량과 비교 → 손익분기물량 이상이면 자가(고정비 높고 변동비 낮은 쪽) 유리."
    },
    {
      "id": "q1-05-10",
      "type": "concept",
      "format": "ox",
      "difficulty": 1,
      "topic": "변동비와 고정비",
      "question": "창고 임차료는 물류량에 비례하여 변동하는 변동비에 해당한다.",
      "options": [],
      "answer": "X",
      "explanation": "창고 임차료는 물류량과 관계없이 계약에 따라 일정하게 발생하는 고정비에 해당한다. 변동비의 예로는 연료비, 포장재료비, 하역인부비 등이 있다.",
      "relatedConcept": "물류원가계산과 손익분석",
      "examTip": "고정비 vs 변동비 구분: 물류량이 변해도 금액이 변하지 않으면 고정비, 물류량에 비례하면 변동비."
    },
    {
      "id": "q1-05-11",
      "type": "exam",
      "format": "multiple_choice",
      "difficulty": 2,
      "topic": "물류비 관리 지표",
      "question": "전기 물류비가 12억 원, 당기 물류비가 10억 원일 때, 물류비 절감률은?",
      "options": [
        "A. 약 10.0%",
        "B. 약 12.5%",
        "C. 약 16.7%",
        "D. 약 20.0%",
        "E. 약 25.0%"
      ],
      "answer": "C",
      "explanation": "물류비 절감률 = (전기물류비 - 당기물류비) ÷ 전기물류비 × 100 = (12억-10억) ÷ 12억 × 100 = 2/12 × 100 ≒ 16.7%.",
      "relatedConcept": "물류회계기준과 물류비 관리",
      "examTip": "물류비 절감률의 분모는 '전기' 물류비이다. 당기를 분모로 착각하지 않도록 주의."
    },
    {
      "id": "q1-05-12",
      "type": "exam",
      "format": "multiple_choice",
      "difficulty": 2,
      "topic": "물류비 산정기준",
      "question": "우리나라 기업물류비 산정기준을 고시하는 기관은?",
      "options": [
        "A. 기획재정부",
        "B. 산업통상자원부",
        "C. 한국은행",
        "D. 국토교통부",
        "E. 통계청"
      ],
      "answer": "D",
      "explanation": "우리나라 기업물류비 산정기준은 국토교통부 고시에 의해 규정된다. 물류정책과 물류비 관리의 주무부처가 국토교통부이기 때문이다.",
      "relatedConcept": "물류회계기준과 물류비 관리",
      "examTip": "물류 관련 주무부처는 국토교통부. 물류비 산정기준, 물류정책기본법 등 물류법규와 연결하여 기억하자."
    },
    {
      "id": "q1-05-13",
      "type": "concept",
      "format": "ox",
      "difficulty": 2,
      "topic": "기회비용과 물류비",
      "question": "재고를 보유함에 따른 기회비용은 기업의 재무회계 상 물류비에 포함되어 인식된다.",
      "options": [],
      "answer": "X",
      "explanation": "이론적으로 재고유지비에는 기회비용이 포함되지만, 실무적 재무회계 상에서는 기회비용을 인식하지 않는다. 기회비용은 관리회계 또는 의사결정 차원에서만 고려된다.",
      "relatedConcept": "물류회계기준과 물류비 관리",
      "examTip": "기회비용은 '이론 vs 실무(재무회계)' 관점에 따라 답이 달라진다. 문제의 맥락을 잘 파악해야 한다."
    },
    {
      "id": "q1-05-14",
      "type": "exam",
      "format": "multiple_choice",
      "difficulty": 2,
      "topic": "예산 편성 방법",
      "question": "매년 제로베이스에서 모든 예산항목을 재검토하여 편성하는 방식으로, 비효율적 관행을 제거하는 데 효과적인 예산 편성 방법은?",
      "options": [
        "A. 증분예산법",
        "B. 고정예산법",
        "C. 변동(탄력)예산법",
        "D. 영기준예산법(ZBB)",
        "E. 성과주의예산법"
      ],
      "answer": "D",
      "explanation": "영기준예산법(ZBB: Zero-Based Budgeting)은 매년 제로(0)에서 출발하여 모든 예산항목의 필요성과 적정성을 재검토하는 방법이다. 관행적 비효율을 제거할 수 있지만, 많은 시간과 노력이 소요되는 단점이 있다.",
      "relatedConcept": "물류회계기준과 물류비 관리",
      "examTip": "'제로베이스', '처음부터 재검토' 키워드 → ZBB. 증분예산은 전년 대비 증감만 조정하는 방식."
    },
    {
      "id": "q1-05-15",
      "type": "exam",
      "format": "multiple_choice",
      "difficulty": 3,
      "topic": "안전한계율 계산",
      "question": "어느 물류센터의 실제 매출액이 2억 원이고 손익분기점 매출액이 1억 5,000만 원일 때, 안전한계율은?",
      "options": [
        "A. 15%",
        "B. 20%",
        "C. 25%",
        "D. 30%",
        "E. 33.3%"
      ],
      "answer": "C",
      "explanation": "안전한계율 = (실제매출액 - BEP매출액) ÷ 실제매출액 × 100 = (2억-1.5억) ÷ 2억 × 100 = 5,000만/2억 × 100 = 25%. 안전한계율이 높을수록 매출 감소에 대한 여유가 크다.",
      "relatedConcept": "물류원가계산과 손익분석",
      "examTip": "안전한계율 분모는 '실제매출액'. BEP매출이 아님에 주의. 이 비율이 높을수록 경영안전도가 높다."
    },
    {
      "id": "q1-05-16",
      "type": "exam",
      "format": "multiple_choice",
      "difficulty": 1,
      "topic": "물류비 영역별 분류",
      "question": "원재료·부품을 공급업체로부터 공장까지 운송·보관하는 과정에서 발생하는 물류비는?",
      "options": [
        "A. 판매물류비",
        "B. 사내물류비",
        "C. 조달물류비",
        "D. 반품물류비",
        "E. 폐기물류비"
      ],
      "answer": "C",
      "explanation": "조달물류비는 원재료·부품을 공급업체로부터 조달(구매)하는 과정에서 발생하는 물류비이다. 판매물류비는 완제품을 고객에게 전달하는 과정, 사내물류비는 공장 내 공정 간 이동에 해당한다.",
      "relatedConcept": "물류비의 개념과 분류체계",
      "examTip": "조달=원재료→공장, 사내=공장 내부, 판매=공장→고객. 물류 흐름을 떠올리면 쉽다."
    },
    {
      "id": "q1-05-17",
      "type": "concept",
      "format": "ox",
      "difficulty": 2,
      "topic": "전통적 원가계산 vs ABC",
      "question": "전통적 원가계산은 다수의 원가동인을 활용하여 ABC보다 정확한 원가배분이 가능하다.",
      "options": [],
      "answer": "X",
      "explanation": "전통적 원가계산은 생산량, 직접노무시간 등 단일 배부기준을 사용하므로 간접비 왜곡이 발생할 수 있다. 다수의 원가동인을 활용하여 보다 정확한 원가배분을 하는 것은 ABC(활동기준원가계산)이다.",
      "relatedConcept": "활동기준원가계산(ABC)",
      "examTip": "다수의 원가동인 = ABC. 단일 배부기준 = 전통적 원가계산. 주어와 서술어를 바꿔놓는 함정에 주의."
    },
    {
      "id": "q1-05-18",
      "type": "exam",
      "format": "multiple_choice",
      "difficulty": 3,
      "topic": "종합 물류비 계산",
      "question": "한 기업의 매출액이 500억 원이고, 총물류비가 40억 원이다. 이 중 운송비 20억, 보관비 10억, 하역비 5억, 포장비 2억, 물류정보비 2억, 물류관리비 1억일 때, 운송비의 물류비 구성비는?",
      "options": [
        "A. 4%",
        "B. 25%",
        "C. 40%",
        "D. 50%",
        "E. 60%"
      ],
      "answer": "D",
      "explanation": "물류비 구성비 = 해당 기능 물류비 ÷ 총물류비 × 100 = 20억 ÷ 40억 × 100 = 50%. 참고로 매출액 대비 물류비율 = 40억/500억 × 100 = 8%이다. 두 지표를 혼동하지 않도록 주의.",
      "relatedConcept": "물류비 산정기준과 물류비 계산",
      "examTip": "구성비: 분모가 '총물류비'. 매출액 대비 비율: 분모가 '매출액'. 무엇을 분모로 하는지가 핵심."
    },
    {
      "id": "q1-05-19",
      "type": "exam",
      "format": "multiple_choice",
      "difficulty": 2,
      "topic": "물류비 지불형태별 분류",
      "question": "자가물류비와 위탁물류비에 대한 설명으로 옳지 않은 것은?",
      "options": [
        "A. 자가물류비는 자사 인력·설비로 물류활동 수행 시 발생한다",
        "B. 위탁물류비는 외부 물류업체에 아웃소싱 시 지불하는 비용이다",
        "C. 자가물류비는 고정비 비중이 높은 편이다",
        "D. 위탁물류비는 물량 변동에 따른 변동비 비중이 높은 편이다",
        "E. 위탁물류비는 자가물류비보다 항상 비용이 저렴하다"
      ],
      "answer": "E",
      "explanation": "위탁물류비가 항상 저렴한 것은 아니다. 소량일 때는 위탁이 유리하지만, 대량일 때는 자가물류가 유리할 수 있다. 비용 유불리는 물류량, 고정비·변동비 구조에 따라 달라진다.",
      "relatedConcept": "물류비의 개념과 분류체계",
      "examTip": "'항상', '반드시' 같은 절대 표현은 오답 신호. 자가 vs 위탁 유불리는 물량에 따라 달라진다."
    },
    {
      "id": "q1-05-20",
      "type": "exam",
      "format": "multiple_choice",
      "difficulty": 3,
      "topic": "물류회계의 과제",
      "question": "물류비 관리의 어려움(물류회계의 과제)에 해당하지 않는 것은?",
      "options": [
        "A. 물류비가 제조원가, 판관비 등 여러 계정에 분산되어 있다",
        "B. 물류비의 범위(어디까지 물류비인지)가 불명확하다",
        "C. 재고보유에 따른 기회비용을 재무회계에 반영하기 어렵다",
        "D. ABC 도입으로 모든 물류비 문제가 완벽하게 해결된다",
        "E. 물류비 산정을 위한 전문 인력·시스템이 부족하다"
      ],
      "answer": "D",
      "explanation": "ABC는 보다 정확한 물류비 배분을 가능하게 하지만, 모든 물류비 문제를 '완벽하게' 해결하는 것은 아니다. ABC도 도입·운영비용, 원가동인 선정의 어려움 등 한계가 있다. A, B, C, E는 물류회계의 대표적 과제에 해당한다.",
      "relatedConcept": "물류회계기준과 물류비 관리",
      "examTip": "'완벽하게 해결', '모든 문제 해결' 같은 과장 표현은 거의 항상 오답. ABC도 만능이 아님을 기억."
    },
    {
      "id": "q1-05-21",
      "type": "exam",
      "format": "multiple_choice",
      "difficulty": 2,
      "topic": "물류비 비중 순서",
      "question": "물류비 기능별 비중이 큰 순서로 올바른 것은?",
      "options": [
        "A. 보관>운송>하역>포장",
        "B. 운송>보관>하역>포장",
        "C. 하역>운송>보관>포장",
        "D. 포장>운송>보관>하역",
        "E. 운송>하역>보관>포장"
      ],
      "answer": "B",
      "explanation": "물류비 비중 순서: 운송>보관>하역>포장>유통가공>물류정보>물류관리. 운송비가 항상 가장 큰 비중을 차지한다.",
      "relatedConcept": "물류비 비중",
      "examTip": "'운보하포유정관' 순서 암기! 운송이 1위, 보관이 2위."
    },
    {
      "id": "q1-05-22",
      "type": "exam",
      "format": "multiple_choice",
      "difficulty": 2,
      "topic": "일반기준 vs 간이기준",
      "question": "물류비 산정에서 간이기준(재무회계방식)의 특징으로 옳지 않은 것은?",
      "options": [
        "A. 재무제표로부터 간단하게 추산한다",
        "B. 중소업체에 적합하다",
        "C. 상세한 물류비 분류 및 계산이 가능하다",
        "D. 전담조직이 없어도 계산이 가능하다",
        "E. 구체적인 성과평가가 어렵다"
      ],
      "answer": "C",
      "explanation": "상세한 물류비 분류 및 계산은 '일반기준(관리회계방식)'의 특징이다. 간이기준은 대략적인 총액계산이 가능하지만 상세 파악은 곤란하다.",
      "relatedConcept": "일반기준 vs 간이기준",
      "examTip": "상세분류=일반기준, 간단추산=간이기준. 특징을 뒤바꾸는 함정!"
    },
    {
      "id": "q1-05-23",
      "type": "exam",
      "format": "multiple_choice",
      "difficulty": 2,
      "topic": "기회원가 적용",
      "question": "물류비 인식에서 기회원가 개념이 적용되는 항목은?",
      "options": [
        "A. 운송비와 포장비",
        "B. 시설부담이자와 재고부담이자",
        "C. 노무비와 재료비",
        "D. 하역비와 유통가공비",
        "E. 물류정보비와 물류관리비"
      ],
      "answer": "B",
      "explanation": "물류비 인식은 발생기준을 준거로 하되, 시설부담이자와 재고부담이자에 대해서만 기회원가 개념을 적용한다.",
      "relatedConcept": "물류비 산정기준",
      "examTip": "기회원가 적용=시설부담이자+재고부담이자 2가지만! 나머지는 발생기준."
    },
    {
      "id": "q1-05-24",
      "type": "exam",
      "format": "multiple_choice",
      "difficulty": 2,
      "topic": "총비용접근법",
      "question": "물류비 관리에서 총비용접근법(Total Cost Approach)의 핵심은?",
      "options": [
        "A. 운송비만 최소화한다",
        "B. 보관비만 최소화한다",
        "C. 개별 물류비가 아닌 총물류비를 최소화한다",
        "D. 물류비보다 매출 극대화를 우선한다",
        "E. 인건비 절감에 집중한다"
      ],
      "answer": "C",
      "explanation": "총비용접근법은 개별 물류비 항목의 최소화가 아닌 전체 물류비(총비용)의 최소화를 추구하는 관점이다. 부분최적화가 아닌 전체최적화가 핵심이다.",
      "relatedConcept": "총비용접근법",
      "examTip": "총비용접근법=전체최적화. 개별비용 최소화≠전체비용 최소화(상충관계 때문)!"
    },
    {
      "id": "q1-05-25",
      "type": "exam",
      "format": "multiple_choice",
      "difficulty": 3,
      "topic": "BEP 매출액 공식",
      "question": "손익분기점 매출액을 구하는 공식은?",
      "options": [
        "A. 총고정비 ÷ (1 - 단위당변동비/단위당판매가격)",
        "B. 총고정비 × 단위당판매가격",
        "C. 총변동비 ÷ 단위당판매가격",
        "D. (총고정비 + 총변동비) × 이익률",
        "E. 총고정비 ÷ 이익률"
      ],
      "answer": "A",
      "explanation": "BEP매출액 = 총고정비 ÷ (1 - 단위당변동비/단위당판매가격) = 총고정비 ÷ 공헌이익률. 공헌이익률 = 1 - 변동비율.",
      "relatedConcept": "손익분기점",
      "examTip": "BEP매출액=총고정비÷공헌이익률. 공헌이익률=1-(변동비/판매가)."
    },
    {
      "id": "q1-05-26",
      "type": "exam",
      "format": "multiple_choice",
      "difficulty": 3,
      "topic": "물류비 레버리지 효과 계산",
      "question": "A기업의 매출액은 5,000억원, 경상이익률 2%, 물류비 비율 10%이다. 물류비를 10% 절감할 때 동일한 경상이익 증가 효과를 얻기 위한 추가 매출액은?",
      "options": [
        "A. 2,000억원",
        "B. 2,500억원",
        "C. 3,000억원",
        "D. 4,000억원",
        "E. 5,000억원"
      ],
      "answer": "B",
      "explanation": "물류비 = 5,000 × 10% = 500억원. 10% 절감 = 50억원 이익 증가. 경상이익률 2%로 50억원 이익을 내려면: 50 ÷ 0.02 = 2,500억원 추가 매출 필요.",
      "relatedConcept": "물류비 레버리지 효과",
      "examTip": "물류비 절감액을 경상이익률로 나누면 동일 효과의 매출액이 산출된다. 물류비 절감의 이익 기여도가 매출 증대보다 크다는 것을 보여주는 대표적 계산문제."
    },
    {
      "id": "q1-05-27",
      "type": "exam",
      "format": "multiple_choice",
      "difficulty": 3,
      "topic": "ABC 원가계산 계산",
      "question": "물류센터에서 피킹 활동의 연간 비용이 2억원이고, 연간 피킹 횟수가 100,000회일 때 활동원가동인율은? A제품의 연간 피킹 횟수가 5,000회라면 A제품에 배부되는 피킹 비용은?",
      "options": [
        "A. 동인율 1,000원, 배부액 500만원",
        "B. 동인율 2,000원, 배부액 1,000만원",
        "C. 동인율 2,000원, 배부액 500만원",
        "D. 동인율 1,500원, 배부액 750만원",
        "E. 동인율 2,500원, 배부액 1,250만원"
      ],
      "answer": "B",
      "explanation": "활동원가동인율 = 2억원 ÷ 100,000회 = 2,000원/회. A제품 배부액 = 2,000원 × 5,000회 = 1,000만원.",
      "relatedConcept": "활동기준원가계산(ABC)",
      "examTip": "ABC 계산은 ①동인율(원가풀÷동인총량) → ②배부액(동인율×소비량) 2단계로 풀이. 단위 환산(억→원)에 주의하자."
    },
    {
      "id": "q1-05-28",
      "type": "exam",
      "format": "multiple_choice",
      "difficulty": 3,
      "topic": "물류비 비율 계산",
      "question": "B기업의 매출액 800억원, 운송비 40억원, 보관비 16억원, 하역비 8억원, 포장비 4억원, 물류정보비 6억원, 물류관리비 6억원이다. 매출액 대비 물류비 비율은?",
      "options": [
        "A. 8%",
        "B. 9%",
        "C. 10%",
        "D. 11%",
        "E. 12%"
      ],
      "answer": "C",
      "explanation": "총 물류비 = 40+16+8+4+6+6 = 80억원. 물류비 비율 = 80/800 × 100 = 10%.",
      "relatedConcept": "물류비 산정기준과 물류비 계산",
      "examTip": "기능별 6분류(운보하포정관)의 합계를 먼저 구한 뒤 매출액으로 나누면 된다. 항목을 빠뜨리지 않도록 하나씩 체크하며 더하자."
    },
    {
      "id": "q1-05-29",
      "type": "exam",
      "format": "multiple_choice",
      "difficulty": 3,
      "topic": "물류비 절감의 이익 기여도 계산",
      "question": "C기업의 매출액 1,000억원, 매출원가율 70%, 물류비율 8%, 영업이익률 5%일 때, 물류비를 5% 절감하면 영업이익은 몇 % 증가하는가?",
      "options": [
        "A. 4%",
        "B. 6%",
        "C. 8%",
        "D. 10%",
        "E. 12%"
      ],
      "answer": "C",
      "explanation": "물류비 = 1,000 × 8% = 80억원. 5% 절감액 = 4억원. 영업이익 = 1,000 × 5% = 50억원. 증가율 = 4/50 × 100 = 8%.",
      "relatedConcept": "물류비 레버리지 효과",
      "examTip": "물류비 절감액이 영업이익에 미치는 영향을 계산하는 문제. 절감액÷영업이익×100으로 증가율을 구한다. 매출원가율은 함정(이 문제에서는 불필요한 정보)."
    },
    {
      "id": "q1-05-30",
      "type": "exam",
      "format": "multiple_choice",
      "difficulty": 3,
      "topic": "손익분기점 물류비 계산",
      "question": "D기업의 고정물류비 12억원, 변동물류비율(매출액 대비) 6%, 매출총이익률 30%일 때, 물류부문 손익분기점 매출액은?",
      "options": [
        "A. 40억원",
        "B. 50억원",
        "C. 60억원",
        "D. 80억원",
        "E. 100억원"
      ],
      "answer": "B",
      "explanation": "손익분기점 = 고정물류비 ÷ (매출총이익률 - 변동물류비율) = 12 ÷ (0.30 - 0.06) = 12 ÷ 0.24 = 50억원.",
      "relatedConcept": "물류원가계산과 손익분석",
      "examTip": "물류부문 BEP 공식: 고정물류비 ÷ (매출총이익률 - 변동물류비율). 분모가 '공헌이익률'이 아닌 '매출총이익률 - 변동물류비율'임에 주의."
    },
    {
      "id": "q1-05-31",
      "type": "exam",
      "format": "multiple_choice",
      "difficulty": 3,
      "topic": "현금전환주기",
      "question": "재고보유일수 40일, 매출채권회수일수 50일, 매입채무지급일수 30일일 때 현금전환주기(C2C)는?",
      "options": [
        "A. 20일",
        "B. 40일",
        "C. 60일",
        "D. 80일",
        "E. 120일"
      ],
      "answer": "C",
      "explanation": "C2C = DIO + DSO - DPO = 40 + 50 - 30 = 60일. 원재료 구매 후 60일 만에 현금을 회수한다.",
      "relatedConcept": "현금전환주기",
      "examTip": "C2C = DIO+DSO-DPO. 매입채무지급일수(DPO)는 '빼기'!"
    },
    {
      "id": "q1-05-32",
      "type": "exam",
      "format": "multiple_choice",
      "difficulty": 2,
      "topic": "ROI",
      "question": "전략적 이익모형(Strategic Profit Model)에서 ROI를 구하는 공식은?",
      "options": [
        "A. 매출이익률 + 자산회전율",
        "B. 매출이익률 × 자산회전율",
        "C. 매출이익률 ÷ 자산회전율",
        "D. 매출액 × 총자산",
        "E. 순이익 + 총자산"
      ],
      "answer": "B",
      "explanation": "전략적 이익모형에서 ROI = 매출이익률 × 자산회전율. 더하기(+)가 아닌 곱하기(×)이다.",
      "relatedConcept": "물류 투자수익률(ROI)",
      "examTip": "ROI=매출이익률×자산회전율. '곱하기'임을 반드시 기억!"
    }
  ]
}